CHANGES.rst
LICENSE
MANIFEST.in
README.rst
setup.cfg
setup.py
tox.ini
docs/CHANGES.rst
docs/README.rst
docs/conf.py
docs/index.rst
docs/_static/.keep
docs/_templates/.keep
src/jt/__init__.py
src/jt/rubicon.cfg
src/jt/rubicon/__about__.py
src/jt/rubicon/__config__.py
src/jt/rubicon/__init__.py
src/jt/rubicon/_java/__init__.py
src/jt/rubicon/_java/class2py.py
src/jt/rubicon/_java/jnirubicon.py
src/jt/rubicon/_java/org/__init__.py
src/jt/rubicon/_java/org/pybee/__init__.py
src/jt/rubicon/_java/org/pybee/rubicon/Python.java
src/jt/rubicon/_java/org/pybee/rubicon/__init__.py
src/jt/rubicon/_java/org/pybee/rubicon/reflect/ProxyHandler.py
src/jt/rubicon/_java/org/pybee/rubicon/reflect/__init__.py
src/jt/rubicon/java/__init__.py
src/jt/rubicon/java/_constants.py
src/jt/rubicon/java/_conversion.py
src/jt/rubicon/java/_exceptions.py
src/jt/rubicon/java/_jclass.py
src/jt/rubicon/java/_jfield.py
src/jt/rubicon/java/_jmethod.py
src/jt/rubicon/java/_jobject.py
src/jt/rubicon/java/_jproxy.py
src/jt/rubicon/java/_jvm.py
src/jt/rubicon/java/_reflect.py
src/jt/rubicon/java/_typemanager.py
src/jt/rubicon/java/jni.py
src/jt/rubicon/java/types.py
src/jt/rubicon/java/_typehandler/__init__.py
src/jt/rubicon/jni/__init__.py
src/jtypes.rubicon.egg-info/PKG-INFO
src/jtypes.rubicon.egg-info/SOURCES.txt
src/jtypes.rubicon.egg-info/dependency_links.txt
src/jtypes.rubicon.egg-info/namespace_packages.txt
src/jtypes.rubicon.egg-info/requires.txt
src/jtypes.rubicon.egg-info/top_level.txt
src/jtypes.rubicon.egg-info/zip-safe
tests/__init__.py
tests/__main__.py
tests/run.py
tests/runner.py
tests/test_jni.py
tests/test_jni.py_
tests/test_rubicon.py
tests/java/classes/com/jt/reflect/ProxyHandler.class
tests/java/classes/org/pybee/rubicon/Python.class
tests/java/classes/org/pybee/rubicon/test/AbstractCallback.class
tests/java/classes/org/pybee/rubicon/test/BaseExample.class
tests/java/classes/org/pybee/rubicon/test/Example$1.class
tests/java/classes/org/pybee/rubicon/test/Example$Inner.class
tests/java/classes/org/pybee/rubicon/test/Example$Stuff.class
tests/java/classes/org/pybee/rubicon/test/Example.class
tests/java/classes/org/pybee/rubicon/test/ICallback.class
tests/java/classes/org/pybee/rubicon/test/Test.class
tests/java/classes/org/pybee/rubicon/test/Thing.class
