Metadata-Version: 2.1
Name: jtypes.rubicon
Version: 0.1.0a2
Summary: A bridge interface between Python and Java (ctypes/cffi-based rubicon-java)
Home-page: http://pypi.python.org/pypi/jtypes.rubicon/
Author: Adam Karpierz
Author-email: adam@karpierz.net
Maintainer: Adam Karpierz
Maintainer-email: adam@karpierz.net
License: BSD license
Download-URL: http://pypi.python.org/pypi/jtypes.rubicon/
Keywords: jtypes, jt, jpype, jep, pyjnius, jpy, javabridge, pyjava, jcc,,py4j, jython, java, pythonjava, rubicon-java
Platform: any
Classifier: Development Status :: 3 - Alpha
Classifier: Intended Audience :: Developers
Classifier: License :: OSI Approved :: BSD License
Classifier: Natural Language :: Polish
Classifier: Operating System :: OS Independent
Classifier: Programming Language :: Java
Classifier: Programming Language :: Python
Classifier: Programming Language :: Python :: 2
Classifier: Programming Language :: Python :: 2.7
Classifier: Programming Language :: Python :: 3
Classifier: Programming Language :: Python :: 3.4
Classifier: Programming Language :: Python :: 3.5
Classifier: Programming Language :: Python :: 3.6
Classifier: Programming Language :: Python :: 3.7
Classifier: Programming Language :: Python :: Implementation :: CPython
Classifier: Programming Language :: Python :: Implementation :: IronPython
Classifier: Programming Language :: Python :: Implementation :: PyPy
Classifier: Programming Language :: Python :: Implementation :: Stackless
Classifier: Topic :: Software Development :: Libraries :: Java Libraries
Classifier: Topic :: Software Development :: Libraries :: Python Modules
Requires-Python: >=2.7.0,!=3.0.*,!=3.1.*,!=3.2.*,!=3.3.*
Provides-Extra: test
Provides-Extra: doc
